hypergal/Host_removing.py
hypergal/PSF_kernel.py
hypergal/__init__.py
hypergal/fit.py
hypergal/fitter.py
hypergal/geometry_tool.py
hypergal/hypergal.py
hypergal/intrinsec_cube.py
hypergal/io.py
hypergal/panstarrs_target.py
hypergal/sed_fitting.py
hypergal/sedm_target.py
hypergal/simulation.py
hypergal/config/cigale.json
hypergal/data/filters/ps1.g.dat
hypergal/data/filters/ps1.i.dat
hypergal/data/filters/ps1.r.dat
hypergal/data/filters/ps1.y.dat
hypergal/data/filters/ps1.z.dat
hypergal/data/filters/ps1_g.dat
hypergal/data/filters/ps1_i.dat
hypergal/data/filters/ps1_r.dat
hypergal/data/filters/ps1_y.dat
hypergal/data/filters/ps1_z.dat
hypergal/data/filters/ztf.g.dat
hypergal/data/filters/ztf.i.dat
hypergal/data/filters/ztf.r.dat
hypergal/data/simulation/Pure_Host_simulation.txt
hypergal/data/simulation/simulation_inputs.csv
hypergal/data/simulation/II_spectra/spec_auto_contsep_lstep1__crr_b_ifu20201011_07_27_41_ZTF20acfdmex.txt
hypergal/data/simulation/II_spectra/spec_auto_contsep_lstep1__crr_b_ifu20210923_11_03_45_ZTF21acaqdee.txt
hypergal/data/simulation/II_spectra/spec_auto_robot_lstep1__crr_b_ifu20191027_04_31_52_ZTF19acgbkzr.txt
hypergal/data/simulation/II_spectra/spec_auto_robot_lstep1__crr_b_ifu20200415_08_48_59_ZTF20aatzhhl.txt
hypergal/data/simulation/II_spectra/spec_auto_robot_lstep1__crr_b_ifu20210923_11_03_45_ZTF21acaqdee.txt
hypergal/data/simulation/II_spectra/spec_auto_robot_lstep1__crr_b_ifu20211212_06_14_11_ZTF21acgqhru.txt
hypergal/data/simulation/Ia_spectra/hgspec_target_crr_b_ifu20180705_10_04_29_ZTF18abdfydj.txt
hypergal/data/simulation/Ia_spectra/hgspec_target_crr_b_ifu20180713_08_20_04_ZTF18abdkimx.txt
hypergal/data/simulation/Ia_spectra/hgspec_target_crr_b_ifu20180721_04_48_17_ZTF18abgledy.txt
hypergal/data/simulation/Ia_spectra/hgspec_target_crr_b_ifu20180721_05_32_10_ZTF18abhpzig.txt
hypergal/data/simulation/Ia_spectra/hgspec_target_crr_b_ifu20180721_07_24_56_ZTF18abfhaji.txt
hypergal-2.0.0.dist-info/LICENSE
hypergal-2.0.0.dist-info/METADATA
hypergal-2.0.0.dist-info/WHEEL
hypergal-2.0.0.dist-info/top_level.txt
hypergal-2.0.0.dist-info/RECORD
